coinselectpy/__init__.py
coinselectpy/accumulative.py
coinselectpy/blackjack.py
coinselectpy/coinselectpy.py
coinselectpy/split.py
coinselectpy/utils.py
coinselectpy-0.1.4.dist-info/AUTHORS.rst
coinselectpy-0.1.4.dist-info/LICENSE
coinselectpy-0.1.4.dist-info/METADATA
coinselectpy-0.1.4.dist-info/WHEEL
coinselectpy-0.1.4.dist-info/entry_points.txt
coinselectpy-0.1.4.dist-info/top_level.txt
coinselectpy-0.1.4.dist-info/RECORD
