Metadata-Version: 2.1
Name: coinselectpy
Version: 0.1.4
Summary: A Python version of https://www.npmjs.com/package/coinselect
Home-page: https://github.com/nextwallet-svr/coinselectpy
Author: Haofu Han
Author-email: gtxx3600@gmail.com
License: MIT license
Keywords: coinselectpy
Platform: UNKNOWN
Classifier: Development Status :: 2 - Pre-Alpha
Classifier: Intended Audience :: Developers
Classifier: License :: OSI Approved :: MIT License
Classifier: Natural Language :: English
Classifier: Programming Language :: Python :: 3
Classifier: Programming Language :: Python :: 3.4
Classifier: Programming Language :: Python :: 3.5
Classifier: Programming Language :: Python :: 3.6
Classifier: Programming Language :: Python :: 3.7
